LICENSE
README.md
setup.cfg
setup.py
HaploDynamics/__init__.py
HaploDynamics.egg-info/PKG-INFO
HaploDynamics.egg-info/SOURCES.txt
HaploDynamics.egg-info/dependency_links.txt
HaploDynamics.egg-info/requires.txt
HaploDynamics.egg-info/top_level.txt
HaploDynamics/Framework/__init__.py
HaploDynamics/Framework/multiproc.py
HaploDynamics/HaploDX/HaploDX.py
HaploDynamics/HaploDX/__init__.py
HaploDynamics/utils/__init__.py
HaploDynamics/utils/load.py