Metadata-Version: 2.1
Name: HaploDynamics
Version: 0.3b1
Summary: A python library to develop genomic data simulators
Home-page: https://github.com/remytuyeras/HaploDynamics
Download-URL: https://github.com/remytuyeras/HaploDynamics/archive/refs/tags/v0.3-beta.1.tar.gz
Author: Remy Tuyeras
Author-email: rtuyeras@gmail.com
License: gpl-3.0
Keywords: Simulator,Genomics,Genomic,Microarray,SNP chip,VCF,Linkage disequilibrium,Hardy-Weinberg equilibrium
Classifier: Development Status :: 4 - Beta
Classifier: Intended Audience :: Developers
Classifier: Intended Audience :: Science/Research
Classifier: Topic :: Software Development :: Build Tools
Classifier: License :: OSI Approved :: GNU General Public License v3 (GPLv3)
Classifier: Programming Language :: Python :: 3
Classifier: Programming Language :: Python :: 3.9
License-File: LICENSE
